freeswitch/sip.py
freeswitch-0.2.1.dist-info/licenses/LICENSE
freeswitch-0.2.1.dist-info/METADATA
freeswitch-0.2.1.dist-info/WHEEL
freeswitch-0.2.1.dist-info/entry_points.txt
freeswitch-0.2.1.dist-info/top_level.txt
freeswitch-0.2.1.dist-info/RECORD
