Metadata-Version: 2.4
Name: freeswitch
Version: 0.2.1
Summary: freeswitch user administrator
Author-email: Neo <netkiller@msn.com>
License-Expression: MIT
Project-URL: Homepage, https://www.netkiller.cn
Project-URL: Issues, https://github.com/netkiller/freeswitch/issues
Classifier: Programming Language :: Python :: 3
Classifier: Operating System :: OS Independent
Requires-Python: >=3.12
License-File: LICENSE
Requires-Dist: texttable
Requires-Dist: tqdm
Requires-Dist: lxml
Dynamic: license-file
